pyflatbush/__init__.py
pyflatbush/flatbush.c
pyflatbush/flatbush.cpython-37m-darwin.so
pyflatbush/flatbush.pyx
pyflatbush/py.typed
pyflatbush-0.1.0.dist-info/LICENSE
pyflatbush-0.1.0.dist-info/METADATA
pyflatbush-0.1.0.dist-info/WHEEL
pyflatbush-0.1.0.dist-info/top_level.txt
pyflatbush-0.1.0.dist-info/RECORD
